lazydev/__init__.py
lazydev/lazydev.py
lazydev_pyunit-2.0.0.dist-info/licenses/LICENSE
tests/__init__.py
tests/test_lazydev.py
lazydev_pyunit-2.0.0.dist-info/METADATA
lazydev_pyunit-2.0.0.dist-info/WHEEL
lazydev_pyunit-2.0.0.dist-info/entry_points.txt
lazydev_pyunit-2.0.0.dist-info/top_level.txt
lazydev_pyunit-2.0.0.dist-info/RECORD
