Metadata-Version: 2.4
Name: lazydev_pyunit
Version: 2.0.0
Summary: A lazy commit message, pull request, excuse and procrastination generator for lazy devs with automated build and test workflows.
Home-page: https://github.com/software-students-spring2025/3-python-package-pyunit
Author: Mahmoud Shehata, Syed Naqvi, Brandon Morales, David Yu
Author-email: Mahmoud Shehata <Mss9253@nyu.edu>, Syed Naqvi <san7576@nyu.edu>, Brandon Morales <bam9516@nyu.edu>, David Yu <dy2262@nyu.edu>
License: MIT License
Project-URL: Homepage, https://github.com/software-students-spring2025/3-python-package-pyunit
Project-URL: Repository, https://github.com/software-students-spring2025/3-python-package-pyunit.git
Project-URL: Bug Tracker, https://github.com/software-students-spring2025/3-python-package-pyunit.git/issues
Keywords: python,automation,git,commit,lazydev
Classifier: Programming Language :: Python :: 3
Classifier: Intended Audience :: Developers
Classifier: License :: OSI Approved :: MIT License
Classifier: Operating System :: OS Independent
Requires-Python: >=3.6
License-File: LICENSE
Provides-Extra: dev
Requires-Dist: pytest; extra == "dev"
Dynamic: author
Dynamic: home-page
Dynamic: license-file
Dynamic: requires-python
